mdx_oembed/__init__.py
mdx_oembed/endpoints.py
mdx_oembed/extension.py
mdx_oembed/inlinepatterns.py
mdx_oembed/version.py
python_markdown_oembed-0.2.1.dist-info/DESCRIPTION.rst
python_markdown_oembed-0.2.1.dist-info/METADATA
python_markdown_oembed-0.2.1.dist-info/RECORD
python_markdown_oembed-0.2.1.dist-info/WHEEL
python_markdown_oembed-0.2.1.dist-info/metadata.json
python_markdown_oembed-0.2.1.dist-info/top_level.txt
