Metadata-Version: 2.0
Name: python-markdown-oembed
Version: 0.2.1
Summary: Markdown extension to allow media embedding using the oEmbed standard.
Home-page: https://github.com/rennat/python-markdown-oembed
Author: Tanner Netterville
Author-email: tannern@gmail.com
License: Public Domain
Keywords: markdown oembed
Platform: UNKNOWN
Classifier: Development Status :: 4 - Beta
Classifier: License :: Public Domain
Classifier: Programming Language :: Python
Classifier: Programming Language :: Python :: 2.7
Classifier: Programming Language :: Python :: 3.2
Classifier: Programming Language :: Python :: 3.3
Classifier: Programming Language :: Python :: 3.4
Classifier: Programming Language :: Python :: 3.5
Requires-Dist: Markdown (>=2.6.1)
Requires-Dist: python-oembed (>=0.2.1)
